example.py
ep_tm/__init__.py
ep_tm-0.0.1.dist-info/LICENSE
ep_tm-0.0.1.dist-info/METADATA
ep_tm-0.0.1.dist-info/WHEEL
ep_tm-0.0.1.dist-info/top_level.txt
ep_tm-0.0.1.dist-info/RECORD
